ct_python/__init__.py
ct_python/api_client.py
ct_python/configuration.py
ct_python/rest.py
ct_python/api/__init__.py
ct_python/api/ct_api.py
ct_python/models/__init__.py
ct_python/models/application.py
ct_python/models/configuration.py
ct_python/models/configuration_file.py
ct_python/models/custom_token_obtain_pair.py
ct_python/models/custom_token_obtain_pair_response.py
ct_python/models/custom_user.py
ct_python/models/environment.py
ct_python/models/organization.py
ct_python/models/organization_group.py
ct_python/models/parent_organization.py
ct_python/models/token_refresh.py
ct_python/models/token_user_response.py
ct_python/models/version.py
ct_python-1.0.3.dist-info/METADATA
ct_python-1.0.3.dist-info/WHEEL
ct_python-1.0.3.dist-info/top_level.txt
ct_python-1.0.3.dist-info/RECORD
