Metadata-Version: 2.1
Name: ct-python
Version: 1.0.3
Summary: ConfigTree API
Home-page: https://configtree.co/
Author-email: info@configtree.co
License: UNKNOWN
Keywords: Swagger,ConfigTree API
Platform: UNKNOWN
Requires-Dist: certifi (==2019.6.16)
Requires-Dist: chardet (==3.0.4)
Requires-Dist: idna (==2.8)
Requires-Dist: nose (==1.3.7)
Requires-Dist: numpy (==1.17.0)
Requires-Dist: python-dateutil (==2.8.0)
Requires-Dist: requests (==2.22.0)
Requires-Dist: six (==1.12.0)
Requires-Dist: urllib3 (==1.25.3)
